{
  "created": 1691318579.340472,
  "duration": 0.9749765396118164,
  "exitcode": 0,
  "root": "B:\\Code\\api_testing_v1\\scenarios",
  "environment": {},
  "summary": { "passed": 3, "total": 3, "collected": 3 },
  "collectors": [
    {
      "nodeid": "",
      "outcome": "passed",
      "result": [{ "nodeid": "get.py", "type": "Module" }]
    },
    {
      "nodeid": "get.py",
      "outcome": "passed",
      "result": [
        { "nodeid": "get.py::test_case1", "type": "Function", "lineno": 14 },
        { "nodeid": "get.py::test_case2", "type": "Function", "lineno": 17 },
        { "nodeid": "get.py::test_case3", "type": "Function", "lineno": 21 }
      ]
    }
  ],
  "tests": [
    {
      "nodeid": "get.py::test_case1",
      "lineno": 14,
      "outcome": "passed",
      "keywords": ["test_case1", "get.py", "scenarios"],
      "setup": { "duration": 0.0005685000214725733, "outcome": "passed" },
      "call": { "duration": 0.0004558999789878726, "outcome": "passed" },
      "teardown": { "duration": 0.00045650004176422954, "outcome": "passed" }
    },
    {
      "nodeid": "get.py::test_case2",
      "lineno": 17,
      "outcome": "passed",
      "keywords": ["test_case2", "get.py", "scenarios"],
      "setup": { "duration": 0.00044919998617842793, "outcome": "passed" },
      "call": { "duration": 0.0004335999838076532, "outcome": "passed" },
      "teardown": { "duration": 0.0004327999777160585, "outcome": "passed" }
    },
    {
      "nodeid": "get.py::test_case3",
      "lineno": 21,
      "outcome": "passed",
      "keywords": ["test_case3", "get.py", "scenarios"],
      "setup": { "duration": 0.00039870000910013914, "outcome": "passed" },
      "call": { "duration": 0.00037949997931718826, "outcome": "passed" },
      "teardown": { "duration": 0.00037560000782832503, "outcome": "passed" }
    }
  ]
}
